anvil/__init__.py
anvil/biome.py
anvil/block.py
anvil/chunk.py
anvil/empty_chunk.py
anvil/empty_region.py
anvil/empty_section.py
anvil/errors.py
anvil/legacy.py
anvil/legacy_biomes.json
anvil/legacy_blocks.json
anvil/raw_section.py
anvil/region.py
anvil/versions.py
anvil_parser2-0.10.6.dist-info/LICENSE
anvil_parser2-0.10.6.dist-info/METADATA
anvil_parser2-0.10.6.dist-info/WHEEL
anvil_parser2-0.10.6.dist-info/top_level.txt
anvil_parser2-0.10.6.dist-info/RECORD
