Metadata-Version: 2.1
Name: anvil-parser2
Version: 0.10.6
Summary: A parser for the Minecraft anvil file format, supports all Minecraft verions
Home-page: https://github.com/0xTiger/anvil-parser2
Author: 0xTiger
License: UNKNOWN
Platform: UNKNOWN
Classifier: Programming Language :: Python :: 3
Classifier: License :: OSI Approved :: MIT License
Classifier: Operating System :: OS Independent
License-File: LICENSE
Requires-Dist: frozendict
Requires-Dist: nbt
